ensurepkg/__init__.py
ensurepkg-0.1.0.dist-info/LICENSE-APACHE
ensurepkg-0.1.0.dist-info/LICENSE-MIT
ensurepkg-0.1.0.dist-info/METADATA
ensurepkg-0.1.0.dist-info/WHEEL
ensurepkg-0.1.0.dist-info/RECORD
