Metadata-Version: 2.1
Name: ensurepkg
Version: 0.1.0
Summary: A minimal package to ensure pip-managed packages on import. Oriented towards scripting in local environments
Author: Yuichiro Smith
Author-email: yu-ichiro@s3i7h.com
Requires-Python: >=3
Classifier: Development Status :: 5 - Production/Stable
Classifier: License :: OSI Approved :: Apache-2.0 License
Classifier: License :: OSI Approved :: MIT License
Classifier: Programming Language :: Python :: 3
Classifier: Programming Language :: Python :: 3.4
Classifier: Programming Language :: Python :: 3.5
Classifier: Programming Language :: Python :: 3.6
Classifier: Programming Language :: Python :: 3.7
Classifier: Programming Language :: Python :: 3.8
Classifier: Programming Language :: Python :: 3.9
Classifier: Programming Language :: Python :: 3.10
Classifier: Programming Language :: Python :: 3.11
Classifier: Programming Language :: Python :: 3.12
Project-URL: Homepage, https://github.com/s3i7h/python-ensurepkg
Project-URL: Issues, https://github.com/s3i7h/python-ensurepkg/issues
Project-URL: Repository, https://github.com/s3i7h/python-ensurepkg.git
